setup.py
spsn_probability/Binomialdistribution.py
spsn_probability/Gaussiandistribution.py
spsn_probability/Generaldistribution.py
spsn_probability/__init__.py
spsn_probability.egg-info/PKG-INFO
spsn_probability.egg-info/SOURCES.txt
spsn_probability.egg-info/dependency_links.txt
spsn_probability.egg-info/not-zip-safe
spsn_probability.egg-info/top_level.txt