Metadata-Version: 1.0
Name: spsn-probability
Version: 0.1
Summary: Gaussian distributions
Home-page: UNKNOWN
Author: Sanmeet Pradhan
Author-email: UNKNOWN
License: UNKNOWN
Platform: UNKNOWN
